pulumi_proxmoxve/__init__.py
pulumi_proxmoxve/_inputs.py
pulumi_proxmoxve/_utilities.py
pulumi_proxmoxve/acl.py
pulumi_proxmoxve/acme_account.py
pulumi_proxmoxve/acme_dns_plugin.py
pulumi_proxmoxve/certifi.py
pulumi_proxmoxve/dns.py
pulumi_proxmoxve/get_container.py
pulumi_proxmoxve/get_containers.py
pulumi_proxmoxve/get_file.py
pulumi_proxmoxve/get_node.py
pulumi_proxmoxve/get_vm2.py
pulumi_proxmoxve/hosts.py
pulumi_proxmoxve/outputs.py
pulumi_proxmoxve/provider.py
pulumi_proxmoxve/pulumi-plugin.json
pulumi_proxmoxve/py.typed
pulumi_proxmoxve/time.py
pulumi_proxmoxve/acme/__init__.py
pulumi_proxmoxve/acme/get_account.py
pulumi_proxmoxve/acme/get_accounts.py
pulumi_proxmoxve/acme/get_plugin.py
pulumi_proxmoxve/acme/get_plugins.py
pulumi_proxmoxve/acme/outputs.py
pulumi_proxmoxve/apt/__init__.py
pulumi_proxmoxve/apt/get_repository.py
pulumi_proxmoxve/apt/repository.py
pulumi_proxmoxve/apt/standard/__init__.py
pulumi_proxmoxve/apt/standard/get_repository.py
pulumi_proxmoxve/apt/standard/repository.py
pulumi_proxmoxve/cluster/__init__.py
pulumi_proxmoxve/cluster/_inputs.py
pulumi_proxmoxve/cluster/get_nodes.py
pulumi_proxmoxve/cluster/options.py
pulumi_proxmoxve/cluster/outputs.py
pulumi_proxmoxve/config/__init__.py
pulumi_proxmoxve/config/__init__.pyi
pulumi_proxmoxve/config/outputs.py
pulumi_proxmoxve/config/vars.py
pulumi_proxmoxve/ct/__init__.py
pulumi_proxmoxve/ct/_inputs.py
pulumi_proxmoxve/ct/container.py
pulumi_proxmoxve/ct/outputs.py
pulumi_proxmoxve/download/__init__.py
pulumi_proxmoxve/download/file.py
pulumi_proxmoxve/ha/__init__.py
pulumi_proxmoxve/ha/get_ha_group.py
pulumi_proxmoxve/ha/get_ha_groups.py
pulumi_proxmoxve/ha/get_ha_resource.py
pulumi_proxmoxve/ha/get_ha_resources.py
pulumi_proxmoxve/ha/ha_group.py
pulumi_proxmoxve/ha/ha_resource.py
pulumi_proxmoxve/hardware/__init__.py
pulumi_proxmoxve/hardware/get_mappings.py
pulumi_proxmoxve/hardware/outputs.py
pulumi_proxmoxve/hardware/mapping/__init__.py
pulumi_proxmoxve/hardware/mapping/_inputs.py
pulumi_proxmoxve-7.11.0.dist-info/METADATA
pulumi_proxmoxve-7.11.0.dist-info/WHEEL
pulumi_proxmoxve-7.11.0.dist-info/top_level.txt
pulumi_proxmoxve-7.11.0.dist-info/RECORD
