Metadata-Version: 2.4
Name: pulumi_proxmoxve
Version: 7.11.0
Summary: A Pulumi package for creating and managing Proxmox Virtual Environment cloud resources.
License: Apache-2.0
Project-URL: Homepage, https://github.com/muhlba91/pulumi-proxmoxve
Project-URL: Repository, https://github.com/muhlba91/pulumi-proxmoxve
Keywords: pulumi,proxmox,proxmoxve
Requires-Python: >=3.9
Requires-Dist: parver>=0.2.1
Requires-Dist: pulumi<4.0.0,>=3.0.0
Requires-Dist: semver>=2.8.1
Requires-Dist: typing-extensions<5,>=4.11; python_version < "3.11"
